boto3_dataclass/__init__.py
boto3_dataclass-1.40.0.dist-info/LICENSE.txt
boto3_dataclass-1.40.0.dist-info/METADATA
boto3_dataclass-1.40.0.dist-info/WHEEL
boto3_dataclass-1.40.0.dist-info/RECORD
